zzd/__init__.py
zzd/cli.py
zzd_cli-0.3.0.dist-info/METADATA
zzd_cli-0.3.0.dist-info/WHEEL
zzd_cli-0.3.0.dist-info/entry_points.txt
zzd_cli-0.3.0.dist-info/top_level.txt
zzd_cli-0.3.0.dist-info/RECORD
