Metadata-Version: 2.1
Name: zzd-cli
Version: 0.3.0
Summary: 走之底科技zzd.show客户端cli
Home-page: UNKNOWN
Author: messizqin
Author-email: 1021358459@qq.com
License: UNKNOWN
Platform: UNKNOWN
Requires-Dist: click
Requires-Dist: requests
Requires-Dist: chardet
Requires-Dist: urllib3 ==1.26.16
Requires-Dist: beautifulsoup4
